scaffolding_python/__init__.py
scaffolding_python/api/__init__.py
scaffolding_python/api/dependencies.py
scaffolding_python/api/routers/__init__.py
scaffolding_python/api/routers/items.py
scaffolding_python/api/routers/users.py
scaffolding_python/combinations_coins/__main__.py
scaffolding_python/combinations_coins/combination_coins.py
scaffolding_python/configs/config_logger.py
scaffolding_python/decorators/__init__.py
scaffolding_python/decorators/error_handling.py
scaffolding_python/error_handling_example.py
scaffolding_python/fibonacci_exercise/__main__.py
scaffolding_python/fibonacci_exercise/fibonacci.py
scaffolding_python/opencensus/custom_event.py
scaffolding_python/opencensus/logs.py
scaffolding_python/script_for_toml.py
scaffolding_python/types/types.py
scaffolding_python-0.1.0.dist-info/entry_points.txt
scaffolding_python-0.1.0.dist-info/METADATA
scaffolding_python-0.1.0.dist-info/WHEEL
scaffolding_python-0.1.0.dist-info/RECORD
