Metadata-Version: 2.1
Name: scaffolding-python
Version: 0.1.0
Summary: 
Author: eduardo.zapata
Author-email: eduardo.zapata@wayops.eu
Requires-Python: >=3.11,<4.0
Classifier: Programming Language :: Python :: 3
Classifier: Programming Language :: Python :: 3.11
Requires-Dist: click (>=8.1.6,<9.0.0)
Requires-Dist: fastapi (>=0.101.0,<0.102.0)
Requires-Dist: opencensus-ext-azure (>=1.1.9,<2.0.0)
Requires-Dist: uvicorn (>=0.23.2,<0.24.0)
